{
    "RegionT1": [
        {
            "Region Code": "44",
            "Region": "Grand Est",
            "Year": "2017",
            "FirstScore": "27.78",
            "Surname": "LE PEN",
            "Name": "Marine",
            "Parti": "FN",
            "SecondScore": "20.72",
            "Surname27": "MACRON",
            "Name27": "Emmanuel",
            "Parti27": "LREM",
            "Year0": "2012",
            "FirstScore0": "28.60384714",
            "Surname0": "SARKOZY",
            "Name0": "Nicolas",
            "Parti0": "UMP",
            "Second Score0": "23.27284962",
            "Surname20": "HOLLANDE",
            "Name20": "François",
            "Parti20": "PS",
            "Year1": "2007",
            "FirstScore1": "32.485302",
            "Surname1": "SARKOZY",
            "Name1": "Nicolas",
            "Parti1": "UMP",
            "Second Score1": "20.75351772",
            "Surname21": "ROYAL",
            "Name21": "Ségolène",
            "Parti21": "PS",
            "Year2": "2002",
            "FirstScore2": "21.91911703",
            "Surname2": "LE PEN",
            "Name2": "JEAN-MARIE",
            "Parti2": "FN",
            "Second Score2": "18.9985881",
            "Surname22": "CHIRAC",
            "Name22": "JACQUES",
            "Parti22": "UMP"
        },
        {
            "Region Code": "75",
            "Region": "Nouvelle-Aquitaine",
            "Year": "2017",
            "FirstScore": "25.12",
            "Surname": "MACRON",
            "Name": "Emmanuel",
            "Parti": "LREM",
            "SecondScore": "20.75",
            "Surname27": "MÉLENCHON",
            "Name27": "Jean-Luc",
            "Parti27": "LFI",
            "Year0": "2012",
            "FirstScore0": "33.22168332",
            "Surname0": "HOLLANDE",
            "Name0": "François",
            "Parti0": "PS",
            "Second Score0": "24.18639117",
            "Surname20": "SARKOZY",
            "Name20": "Nicolas",
            "Parti20": "UMP",
            "Year1": "2007",
            "FirstScore1": "30.04467499",
            "Surname1": "ROYAL",
            "Name1": "Ségolène",
            "Parti1": "PS",
            "Second Score1": "27.70062967",
            "Surname21": "SARKOZY",
            "Name21": "Nicolas",
            "Parti21": "UMP",
            "Year2": "2002",
            "FirstScore2": "22.80661566",
            "Surname2": "CHIRAC",
            "Name2": "JACQUES",
            "Parti2": "LR",
            "Second Score2": "17.52652875",
            "Surname22": "JOSPIN",
            "Name22": "LIONEL",
            "Parti22": "PS"
        },
        {
            "Region Code": "84",
            "Region": "Auvergne et Rhône-Alpes",
            "Year": "2017",
            "FirstScore": "24.5",
            "Surname": "MACRON",
            "Name": "Emmanuel",
            "Parti": "LREM",
            "SecondScore": "20.72",
            "Surname27": "LE PEN",
            "Name27": "Marine",
            "Parti27": "FN",
            "Year0": "2012",
            "FirstScore0": "27.4029851",
            "Surname0": "SARKOZY",
            "Name0": "Nicolas",
            "Parti0": "UMP",
            "Second Score0": "26.47841328",
            "Surname20": "HOLLANDE",
            "Name20": "François",
            "Parti20": "PS",
            "Year1": "2007",
            "FirstScore1": "31.75318511",
            "Surname1": "SARKOZY",
            "Name1": "Nicolas",
            "Parti1": "UMP",
            "Second Score1": "24.11501287",
            "Surname21": "ROYAL",
            "Name21": "Ségolène",
            "Parti21": "PS",
            "Year2": "2002",
            "FirstScore2": "18.67253105",
            "Surname2": "LE PEN",
            "Name2": "JEAN-MARIE",
            "Parti2": "FN",
            "Second Score2": "17.97899804",
            "Surname22": "CHIRAC",
            "Name22": "JACQUES",
            "Parti22": "UMP"
        },
        {
            "Region Code": "27",
            "Region": "Bourgogne-Franche-Comté",
            "Year": "2017",
            "FirstScore": "25.09",
            "Surname": "LE PEN",
            "Name": "Marine",
            "Parti": "FN",
            "SecondScore": "21.89",
            "Surname27": "MACRON",
            "Name27": "Emmanuel",
            "Parti27": "LREM",
            "Year0": "2012",
            "FirstScore0": "27.11595067",
            "Surname0": "HOLLANDE",
            "Name0": "François",
            "Parti0": "PS",
            "Second Score0": "26.64544536",
            "Surname20": "SARKOZY",
            "Name20": "Nicolas",
            "Parti20": "UMP",
            "Year1": "2007",
            "FirstScore1": "30.69805476",
            "Surname1": "SARKOZY",
            "Name1": "Nicolas",
            "Parti1": "UMP",
            "Second Score1": "24.46569822",
            "Surname21": "ROYAL",
            "Name21": "Ségolène",
            "Parti21": "PS",
            "Year2": "2002",
            "FirstScore2": "18.97515219",
            "Surname2": "LE PEN",
            "Name2": "JEAN-MARIE",
            "Parti2": "FN",
            "Second Score2": "18.47432001",
            "Surname22": "CHIRAC",
            "Name22": "JACQUES",
            "Parti22": "UMP"
        },
        {
            "Region Code": "53",
            "Region": "Bretagne",
            "Year": "2017",
            "FirstScore": "29.05",
            "Surname": "MACRON",
            "Name": "Emmanuel",
            "Parti": "LREM",
            "SecondScore": "19.28",
            "Surname27": "MÉLENCHON",
            "Name27": "Jean-Luc",
            "Parti27": "LFI",
            "Year0": "2012",
            "FirstScore0": "31.74",
            "Surname0": "HOLLANDE",
            "Name0": "François",
            "Parti0": "PS",
            "Second Score0": "25.66",
            "Surname20": "SARKOZY",
            "Name20": "Nicolas",
            "Parti20": "UMP",
            "Year1": "2007",
            "FirstScore1": "28.14",
            "Surname1": "ROYAL",
            "Name1": "Ségolène",
            "Parti1": "PS",
            "Second Score1": "27.81",
            "Surname21": "SARKOZY",
            "Name21": "Nicolas",
            "Parti21": "UMP",
            "Year2": "2002",
            "FirstScore2": "21.6",
            "Surname2": "CHIRAC",
            "Name2": "JACQUES",
            "Parti2": "LR",
            "Second Score2": "18.07",
            "Surname22": "JOSPIN",
            "Name22": "LIONEL",
            "Parti22": "PS"
        },
        {
            "Region Code": "24",
            "Region": "Centre-Val de Loire",
            "Year": "2017",
            "FirstScore": "23.08",
            "Surname": "LE PEN",
            "Name": "Marine",
            "Parti": "FN",
            "SecondScore": "22.68",
            "Surname27": "MACRON",
            "Name27": "Emmanuel",
            "Parti27": "LREM",
            "Year0": "2012",
            "FirstScore0": "28.53",
            "Surname0": "SARKOZY",
            "Name0": "Nicolas",
            "Parti0": "UMP",
            "Second Score0": "24.76",
            "Surname20": "HOLLANDE",
            "Name20": "François",
            "Parti20": "PS",
            "Year1": "2007",
            "FirstScore1": "32.74",
            "Surname1": "SARKOZY",
            "Name1": "Nicolas",
            "Parti1": "UMP",
            "Second Score1": "21.27",
            "Surname21": "ROYAL",
            "Name21": "Ségolène",
            "Parti21": "PS",
            "Year2": "2002",
            "FirstScore2": "21.12",
            "Surname2": "LE PEN",
            "Name2": "JEAN-MARIE",
            "Parti2": "FN",
            "Second Score2": "19.97",
            "Surname22": "CHIRAC",
            "Name22": "JACQUES",
            "Parti22": "UMP"
        },
        {
            "Region Code": "11",
            "Region": "Île-de-France",
            "Year": "2017",
            "FirstScore": "28.63",
            "Surname": "MACRON",
            "Name": "Emmanuel",
            "Parti": "LREM",
            "SecondScore": "22.19",
            "Surname27": "FILLON",
            "Name27": "François",
            "Parti27": "LR",
            "Year0": "2012",
            "FirstScore0": "26.64",
            "Surname0": "SARKOZY",
            "Name0": "Nicolas",
            "Parti0": "UMP",
            "Second Score0": "25.89",
            "Surname20": "HOLLANDE",
            "Name20": "François",
            "Parti20": "PS",
            "Year1": "2007",
            "FirstScore1": "30.93",
            "Surname1": "SARKOZY",
            "Name1": "Nicolas",
            "Parti1": "UMP",
            "Second Score1": "24.07",
            "Surname21": "ROYAL",
            "Name21": "Ségolène",
            "Parti21": "PS",
            "Year2": "2002",
            "FirstScore2": "19.98",
            "Surname2": "LE PEN",
            "Name2": "JEAN-MARIE",
            "Parti2": "FN",
            "Second Score2": "17.7",
            "Surname22": "CHIRAC",
            "Name22": "JACQUES",
            "Parti22": "UMP"
        },
        {
            "Region Code": "76",
            "Region": "Occitanie",
            "Year": "2017",
            "FirstScore": "22.98",
            "Surname": "LE PEN",
            "Name": "Marine",
            "Parti": "FN",
            "SecondScore": "22.32",
            "Surname27": "MACRON",
            "Name27": "Emmanuel",
            "Parti27": "LREM",
            "Year0": "2012",
            "FirstScore0": "29.27351767",
            "Surname0": "HOLLANDE",
            "Name0": "François",
            "Parti0": "PS",
            "Second Score0": "23.79671037",
            "Surname20": "SARKOZY",
            "Name20": "Nicolas",
            "Parti20": "UMP",
            "Year1": "2007",
            "FirstScore1": "28.54450137",
            "Surname1": "ROYAL",
            "Name1": "Ségolène",
            "Parti1": "PS",
            "Second Score1": "28.25715318",
            "Surname21": "SARKOZY",
            "Name21": "Nicolas",
            "Parti21": "UMP",
            "Year2": "2002",
            "FirstScore2": "18.55650981",
            "Surname2": "LE PEN",
            "Name2": "JEAN-MARIE",
            "Parti2": "FN",
            "Second Score2": "17.99109809",
            "Surname22": "JOSPIN",
            "Name22": "LIONEL",
            "Parti22": "PS"
        },
        {
            "Region Code": "32",
            "Region": "Hauts-de-France",
            "Year": "2017",
            "FirstScore": "31.04",
            "Surname": "LE PEN",
            "Name": "Marine",
            "Parti": "FN",
            "SecondScore": "19.59",
            "Surname27": "MÉLENCHON",
            "Name27": "Jean-Luc",
            "Parti27": "LFI",
            "Year0": "2012",
            "FirstScore0": "27.90330912",
            "Surname0": "HOLLANDE",
            "Name0": "François",
            "Parti0": "PS",
            "Second Score0": "24.0929824",
            "Surname20": "SARKOZY",
            "Name20": "Nicolas",
            "Parti20": "UMP",
            "Year1": "2007",
            "FirstScore1": "28.67602083",
            "Surname1": "SARKOZY",
            "Name1": "Nicolas",
            "Parti1": "UMP",
            "Second Score1": "24.37646307",
            "Surname21": "ROYAL",
            "Name21": "Ségolène",
            "Parti21": "PS",
            "Year2": "2002",
            "FirstScore2": "19.43249945",
            "Surname2": "LE PEN",
            "Name2": "JEAN-MARIE",
            "Parti2": "FN",
            "Second Score2": "17.5931586",
            "Surname22": "CHIRAC",
            "Name22": "JACQUES",
            "Parti22": "UMP"
        },
        {
            "Region Code": "28",
            "Region": "Normandie",
            "Year": "2017",
            "FirstScore": "23.93",
            "Surname": "LE PEN",
            "Name": "Marine",
            "Parti": "FN",
            "SecondScore": "22.36",
            "Surname27": "MACRON",
            "Name27": "Emmanuel",
            "Parti27": "LREM",
            "Year0": "2012",
            "FirstScore0": "27.71135904",
            "Surname0": "HOLLANDE",
            "Name0": "François",
            "Parti0": "PS",
            "Second Score0": "27.0203763",
            "Surname20": "SARKOZY",
            "Name20": "Nicolas",
            "Parti20": "UMP",
            "Year1": "2007",
            "FirstScore1": "30.05583782",
            "Surname1": "SARKOZY",
            "Name1": "Nicolas",
            "Parti1": "UMP",
            "Second Score1": "23.75991622",
            "Surname21": "ROYAL",
            "Name21": "Ségolène",
            "Parti21": "PS",
            "Year2": "2002",
            "FirstScore2": "20.62745264",
            "Surname2": "CHIRAC",
            "Name2": "JACQUES",
            "Parti2": "UMP",
            "Second Score2": "16.11087434",
            "Surname22": "LE PEN",
            "Name22": "JEAN-MARIE",
            "Parti22": "FN"
        },
        {
            "Region Code": "52",
            "Region": "Pays de la Loire",
            "Year": "2017",
            "FirstScore": "26.27",
            "Surname": "MACRON",
            "Name": "Emmanuel",
            "Parti": "LREM",
            "SecondScore": "23.56",
            "Surname27": "FILLON",
            "Name27": "François",
            "Parti27": "LR",
            "Year0": "2012",
            "FirstScore0": "31.9",
            "Surname0": "HOLLANDE",
            "Name0": "François",
            "Parti0": "PS",
            "Second Score0": "22.94",
            "Surname20": "SARKOZY",
            "Name20": "Nicolas",
            "Parti20": "UMP",
            "Year1": "2007",
            "FirstScore1": "31.11",
            "Surname1": "ROYAL",
            "Name1": "Ségolène",
            "Parti1": "PS",
            "Second Score1": "26.29",
            "Surname21": "SARKOZY",
            "Name21": "Nicolas",
            "Parti21": "UMP",
            "Year2": "2002",
            "FirstScore2": "19.53",
            "Surname2": "JOSPIN",
            "Name2": "LIONEL",
            "Parti2": "PS",
            "Second Score2": "17.12",
            "Surname22": "CHIRAC",
            "Name22": "JACQUES",
            "Parti22": "UMP"
        },
        {
            "Region Code": "93",
            "Region": "Provence-Alpes-Côte d'Azur",
            "Year": "2017",
            "FirstScore": "28.16",
            "Surname": "LE PEN",
            "Name": "Marine",
            "Parti": "FN",
            "SecondScore": "22.38",
            "Surname27": "FILLON",
            "Name27": "François",
            "Parti27": "LR",
            "Year0": "2012",
            "FirstScore0": "28.53",
            "Surname0": "HOLLANDE",
            "Name0": "François",
            "Parti0": "PS",
            "Second Score0": "23.62",
            "Surname20": "SARKOZY",
            "Name20": "Nicolas",
            "Parti20": "UMP",
            "Year1": "2007",
            "FirstScore1": "27.92",
            "Surname1": "SARKOZY",
            "Name1": "Nicolas",
            "Parti1": "UMP",
            "Second Score1": "25.02",
            "Surname21": "ROYAL",
            "Name21": "Ségolène",
            "Parti21": "PS",
            "Year2": "2002",
            "FirstScore2": "19.04",
            "Surname2": "LE PEN",
            "Name2": "JEAN-MARIE",
            "Parti2": "FN",
            "Second Score2": "17.29",
            "Surname22": "CHIRAC",
            "Name22": "JACQUES",
            "Parti22": "UMP"
        },
        {
            "Region Code": "94",
            "Region": "Corse",
            "Year": "2017",
            "FirstScore": "27.88",
            "Surname": "LE PEN",
            "Name": "Marine",
            "Parti": "FN",
            "SecondScore": "25.56",
            "Surname27": "FILLON",
            "Name27": "François",
            "Parti27": "LR",
            "Year0": "2012",
            "FirstScore0": "28.31",
            "Surname0": "SARKOZY",
            "Name0": "Nicolas",
            "Parti0": "UMP",
            "Second Score0": "27.54",
            "Surname20": "HOLLANDE",
            "Name20": "François",
            "Parti20": "PS",
            "Year1": "2007",
            "FirstScore1": "30.84",
            "Surname1": "SARKOZY",
            "Name1": "Nicolas",
            "Parti1": "UMP",
            "Second Score1": "22.99",
            "Surname21": "ROYAL",
            "Name21": "Ségolène",
            "Parti21": "PS",
            "Year2": "2002",
            "FirstScore2": "22.37",
            "Surname2": "CHIRAC",
            "Name2": "JACQUES",
            "Parti2": "UMP",
            "Second Score2": "14.74",
            "Surname22": "LE PEN",
            "Name22": "JEAN-MARIE",
            "Parti22": "FN"
        },
        {
            "Region Code": "1",
            "Region": "Guadeloupe",
            "Year": "2017",
            "FirstScore": "30.23",
            "Surname": "MACRON",
            "Name": "Emmanuel",
            "Parti": "LREM",
            "SecondScore": "24.13",
            "Surname27": "MÉLENCHON",
            "Name27": "Jean-Luc",
            "Parti27": "LFI",
            "Year0": "2012",
            "FirstScore0": "27.86",
            "Surname0": "HOLLANDE",
            "Name0": "François",
            "Parti0": "PS",
            "Second Score0": "25.92",
            "Surname20": "SARKOZY",
            "Name20": "Nicolas",
            "Parti20": "UMP",
            "Year1": "2007",
            "FirstScore1": "29.38",
            "Surname1": "SARKOZY",
            "Name1": "Nicolas",
            "Parti1": "UMP",
            "Second Score1": "24.42",
            "Surname21": "ROYAL",
            "Name21": "Ségolène",
            "Parti21": "PS",
            "Year2": "2002",
            "FirstScore2": "19.15",
            "Surname2": "CHIRAC",
            "Name2": "JACQUES",
            "Parti2": "UMP",
            "Second Score2": "17.27",
            "Surname22": "LE PEN",
            "Name22": "JEAN-MARIE",
            "Parti22": "FN"
        },
        {
            "Region Code": "2",
            "Region": "Martinique",
            "Year": "2017",
            "FirstScore": "27.37",
            "Surname": "MÉLENCHON",
            "Name": "Jean-Luc",
            "Parti": "LFI",
            "SecondScore": "25.53",
            "Surname27": "MACRON",
            "Name27": "Emmanuel",
            "Parti27": "LREM",
            "Year0": "2012",
            "FirstScore0": "28.63",
            "Surname0": "SARKOZY",
            "Name0": "Nicolas",
            "Parti0": "UMP",
            "Second Score0": "28.4",
            "Surname20": "HOLLANDE",
            "Name20": "François",
            "Parti20": "PS",
            "Year1": "2007",
            "FirstScore1": "29.48",
            "Surname1": "SARKOZY",
            "Name1": "Nicolas",
            "Parti1": "UMP",
            "Second Score1": "25.56",
            "Surname21": "ROYAL",
            "Name21": "Ségolène",
            "Parti21": "PS",
            "Year2": "2002",
            "FirstScore2": "21.68",
            "Surname2": "CHIRAC",
            "Name2": "JACQUES",
            "Parti2": "UMP",
            "Second Score2": "16.19",
            "Surname22": "JOSPIN",
            "Name22": "LIONEL",
            "Parti22": "PS"
        },
        {
            "Region Code": "3",
            "Region": "Guyane",
            "Year": "2017",
            "FirstScore": "24.71",
            "Surname": "MÉLENCHON",
            "Name": "Jean-Luc",
            "Parti": "LFI",
            "SecondScore": "24.3",
            "Surname27": "LE PEN",
            "Name27": "Marine",
            "Parti27": "FN",
            "Year0": "2012",
            "FirstScore0": "26.59",
            "Surname0": "HOLLANDE",
            "Name0": "François",
            "Parti0": "PS",
            "Second Score0": "25.09",
            "Surname20": "SARKOZY",
            "Name20": "Nicolas",
            "Parti20": "UMP",
            "Year1": "2007",
            "FirstScore1": "30.27",
            "Surname1": "SARKOZY",
            "Name1": "Nicolas",
            "Parti1": "UMP",
            "Second Score1": "23.02",
            "Surname21": "ROYAL",
            "Name21": "Ségolène",
            "Parti21": "PS",
            "Year2": "2002",
            "FirstScore2": "20.26",
            "Surname2": "LE PEN",
            "Name2": "JEAN-MARIE",
            "Parti2": "LFI",
            "Second Score2": "18.22",
            "Surname22": "CHIRAC",
            "Name22": "JACQUES",
            "Parti22": "UMP"
        },
        {
            "Region Code": "4",
            "Region": "La Réunion",
            "Year": "2017",
            "FirstScore": "24.53",
            "Surname": "MÉLENCHON",
            "Name": "Jean-Luc",
            "Parti": "LFI",
            "SecondScore": "23.46",
            "Surname27": "LE PEN",
            "Name27": "Marine",
            "Parti27": "FN",
            "Year0": "2012",
            "FirstScore0": "31.17",
            "Surname0": "HOLLANDE",
            "Name0": "François",
            "Parti0": "PS",
            "Second Score0": "25.61",
            "Surname20": "SARKOZY",
            "Name20": "Nicolas",
            "Parti20": "UMP",
            "Year1": "2007",
            "FirstScore1": "29.87",
            "Surname1": "ROYAL",
            "Name1": "Ségolène",
            "Parti1": "PS",
            "Second Score1": "28.22",
            "Surname21": "SARKOZY",
            "Name21": "Nicolas",
            "Parti21": "UMP",
            "Year2": "2002",
            "FirstScore2": "20.9",
            "Surname2": "CHIRAC",
            "Name2": "JACQUES",
            "Parti2": "UMP",
            "Second Score2": "17.17",
            "Surname22": "JOSPIN",
            "Name22": "LIONEL",
            "Parti22": "PS"
        },
        {
            "Region Code": "6",
            "Region": "Mayotte",
            "Year": "2017",
            "FirstScore": "32.62",
            "Surname": "FILLON",
            "Name": "François",
            "Parti": "LR",
            "SecondScore": "27.19",
            "Surname27": "LE PEN",
            "Name27": "Marine",
            "Parti27": "FN",
            "Year0": "2012",
            "FirstScore0": "31.06",
            "Surname0": "SARKOZY",
            "Name0": "Nicolas",
            "Parti0": "UMP",
            "Second Score0": "23.87",
            "Surname20": "LE PEN",
            "Name20": "Marine",
            "Parti20": "FN",
            "Year1": "2007",
            "FirstScore1": "37.01",
            "Surname1": "SARKOZY",
            "Name1": "Nicolas",
            "Parti1": "UMP",
            "Second Score1": "21.21",
            "Surname21": "ROYAL",
            "Name21": "Ségolène",
            "Parti21": "PS",
            "Year2": "2002",
            "FirstScore2": "23.35",
            "Surname2": "LE PEN",
            "Name2": "JEAN-MARIE",
            "Parti2": "LFI",
            "Second Score2": "18.92",
            "Surname22": "CHIRAC",
            "Name22": "JACQUES",
            "Parti22": "UMP"
        }
    ]
}